{"nodes": [{"id": "landing_page", "label": "Public Landing Page (torqr.de)", "file_type": "code", "source_file": ".graphify-marketing-staging/code/landing-page.tsx", "source_location": null, "source_url": null, "captured_at": null, "author": null, "contributor": null}, {"id": "page:Home", "label": "Home (landing-page.tsx)", "file_type": "code", "source_file": ".graphify-marketing-staging/code/landing-page.tsx", "source_location": null, "source_url": null, "captured_at": null, "author": null, "contributor": null}, {"id": "section:Hero", "label": "Hero", "file_type": "code", "source_file": ".graphify-marketing-staging/code/landing-page.tsx", "source_location": null, "source_url": null, "captured_at": null, "author": null, "contributor": null}, {"id": "section:PainBlock", "label": "PainBlock", "file_type": "code", "source_file": ".graphify-marketing-staging/code/landing-page.tsx", "source_location": null, "source_url": null, "captured_at": null, "author": null, "contributor": null}, {"id": "section:ThreeStepSolution", "label": "ThreeStepSolution", "file_type": "code", "source_file": ".graphify-marketing-staging/code/landing-page.tsx", "source_location": null, "source_url": null, "captured_at": null, "author": null, "contributor": null}, {"id": "section:FeatureSection", "label": "FeatureSection", "file_type": "code", "source_file": ".graphify-marketing-staging/code/landing-page.tsx", "source_location": null, "source_url": null, "captured_at": null, "author": null, "contributor": null}, {"id": "section:RoiBlock", "label": "RoiBlock", "file_type": "code", "source_file": ".graphify-marketing-staging/code/landing-page.tsx", "source_location": null, "source_url": null, "captured_at": null, "author": null, "contributor": null}, {"id": "section:PilotStatus", "label": "PilotStatus", "file_type": "code", "source_file": ".graphify-marketing-staging/code/landing-page.tsx", "source_location": null, "source_url": null, "captured_at": null, "author": null, "contributor": null}, {"id": "section:TrustBlock", "label": "TrustBlock", "file_type": "code", "source_file": ".graphify-marketing-staging/code/landing-page.tsx", "source_location": null, "source_url": null, "captured_at": null, "author": null, "contributor": null}, {"id": "section:Pricing", "label": "Pricing", "file_type": "code", "source_file": ".graphify-marketing-staging/code/landing-page.tsx", "source_location": null, "source_url": null, "captured_at": null, "author": null, "contributor": null}, {"id": "section:Faq", "label": "Faq", "file_type": "code", "source_file": ".graphify-marketing-staging/code/landing-page.tsx", "source_location": null, "source_url": null, "captured_at": null, "author": null, "contributor": null}, {"id": "section:FinalCta", "label": "FinalCta", "file_type": "code", "source_file": ".graphify-marketing-staging/code/landing-page.tsx", "source_location": null, "source_url": null, "captured_at": null, "author": null, "contributor": null}, {"id": "meta:Schema.SoftwareApplication", "label": "Schema.org SoftwareApplication JSON-LD", "file_type": "code", "source_file": ".graphify-marketing-staging/code/landing-page.tsx", "source_location": null, "source_url": null, "captured_at": null, "author": null, "contributor": null}], "edges": [{"source": "page:Home", "target": "comp:MarketingHeader", "relation": "references", "confidence": "EXTRACTED", "confidence_score": 1.0, "source_file": ".graphify-marketing-staging/code/landing-page.tsx", "source_location": null, "weight": 1.0}, {"source": "page:Home", "target": "comp:MarketingFooter", "relation": "references", "confidence": "EXTRACTED", "confidence_score": 1.0, "source_file": ".graphify-marketing-staging/code/landing-page.tsx", "source_location": null, "weight": 1.0}, {"source": "page:Home", "target": "section:Hero", "relation": "composes_section", "confidence": "EXTRACTED", "confidence_score": 1.0, "source_file": ".graphify-marketing-staging/code/landing-page.tsx", "source_location": null, "weight": 1.0}, {"source": "page:Home", "target": "section:PainBlock", "relation": "composes_section", "confidence": "EXTRACTED", "confidence_score": 1.0, "source_file": ".graphify-marketing-staging/code/landing-page.tsx", "source_location": null, "weight": 1.0}, {"source": "page:Home", "target": "section:ThreeStepSolution", "relation": "composes_section", "confidence": "EXTRACTED", "confidence_score": 1.0, "source_file": ".graphify-marketing-staging/code/landing-page.tsx", "source_location": null, "weight": 1.0}, {"source": "page:Home", "target": "section:FeatureSection", "relation": "composes_section", "confidence": "EXTRACTED", "confidence_score": 1.0, "source_file": ".graphify-marketing-staging/code/landing-page.tsx", "source_location": null, "weight": 1.0}, {"source": "page:Home", "target": "section:RoiBlock", "relation": "composes_section", "confidence": "EXTRACTED", "confidence_score": 1.0, "source_file": ".graphify-marketing-staging/code/landing-page.tsx", "source_location": null, "weight": 1.0}, {"source": "page:Home", "target": "section:PilotStatus", "relation": "composes_section", "confidence": "EXTRACTED", "confidence_score": 1.0, "source_file": ".graphify-marketing-staging/code/landing-page.tsx", "source_location": null, "weight": 1.0}, {"source": "page:Home", "target": "section:TrustBlock", "relation": "composes_section", "confidence": "EXTRACTED", "confidence_score": 1.0, "source_file": ".graphify-marketing-staging/code/landing-page.tsx", "source_location": null, "weight": 1.0}, {"source": "page:Home", "target": "section:Pricing", "relation": "composes_section", "confidence": "EXTRACTED", "confidence_score": 1.0, "source_file": ".graphify-marketing-staging/code/landing-page.tsx", "source_location": null, "weight": 1.0}, {"source": "page:Home", "target": "section:Faq", "relation": "composes_section", "confidence": "EXTRACTED", "confidence_score": 1.0, "source_file": ".graphify-marketing-staging/code/landing-page.tsx", "source_location": null, "weight": 1.0}, {"source": "page:Home", "target": "section:FinalCta", "relation": "composes_section", "confidence": "EXTRACTED", "confidence_score": 1.0, "source_file": ".graphify-marketing-staging/code/landing-page.tsx", "source_location": null, "weight": 1.0}, {"source": "page:Home", "target": "meta:Schema.SoftwareApplication", "relation": "references", "confidence": "EXTRACTED", "confidence_score": 1.0, "source_file": ".graphify-marketing-staging/code/landing-page.tsx", "source_location": null, "weight": 1.0}, {"source": "page:Home", "target": "ext:auth", "relation": "references", "confidence": "EXTRACTED", "confidence_score": 1.0, "source_file": ".graphify-marketing-staging/code/landing-page.tsx", "source_location": null, "weight": 1.0}], "hyperedges": [{"id": "hyper:landing-composition", "label": "Landing-Page Composition (Home \u2192 10 marketing sections)", "members": ["page:Home", "section:Hero", "section:PainBlock", "section:ThreeStepSolution", "section:FeatureSection", "section:RoiBlock", "section:PilotStatus", "section:TrustBlock", "section:Pricing", "section:Faq", "section:FinalCta", "comp:MarketingHeader", "comp:MarketingFooter"], "relation": "composes_section", "confidence": "EXTRACTED", "confidence_score": 1.0, "source_file": ".graphify-marketing-staging/code/landing-page.tsx"}]}