{"nodes": [{"id": "comp:MarketingHeader", "label": "MarketingHeader", "file_type": "code", "source_file": ".graphify-marketing-staging/code/MarketingHeader.tsx", "source_location": null, "source_url": null, "captured_at": null, "author": null, "contributor": null}, {"id": "nav:anchor#features", "label": "#features (anchor)", "file_type": "code", "source_file": ".graphify-marketing-staging/code/MarketingHeader.tsx", "source_location": null, "source_url": null, "captured_at": null, "author": null, "contributor": null}, {"id": "nav:anchor#pricing", "label": "#pricing (anchor)", "file_type": "code", "source_file": ".graphify-marketing-staging/code/MarketingHeader.tsx", "source_location": null, "source_url": null, "captured_at": null, "author": null, "contributor": null}, {"id": "nav:anchor#faq", "label": "#faq (anchor)", "file_type": "code", "source_file": ".graphify-marketing-staging/code/MarketingHeader.tsx", "source_location": null, "source_url": null, "captured_at": null, "author": null, "contributor": null}, {"id": "nav:anchor#cta", "label": "#cta (anchor)", "file_type": "code", "source_file": ".graphify-marketing-staging/code/MarketingHeader.tsx", "source_location": null, "source_url": null, "captured_at": null, "author": null, "contributor": null}, {"id": "nav:link/dashboard", "label": "/dashboard (link)", "file_type": "code", "source_file": ".graphify-marketing-staging/code/MarketingHeader.tsx", "source_location": null, "source_url": null, "captured_at": null, "author": null, "contributor": null}, {"id": "nav:link/login", "label": "/login (link)", "file_type": "code", "source_file": ".graphify-marketing-staging/code/MarketingHeader.tsx", "source_location": null, "source_url": null, "captured_at": null, "author": null, "contributor": null}, {"id": "brand:voice.cta.30days", "label": "CTA: 30 Tage testen", "file_type": "code", "source_file": ".graphify-marketing-staging/code/MarketingHeader.tsx", "source_location": null, "source_url": null, "captured_at": null, "author": null, "contributor": null}, {"id": "ext:auth", "label": "@/lib/auth (auth())", "file_type": "code", "source_file": ".graphify-marketing-staging/code/MarketingHeader.tsx", "source_location": null, "source_url": null, "captured_at": null, "author": null, "contributor": null}, {"id": "ext:Button", "label": "@/components/ui/button", "file_type": "code", "source_file": ".graphify-marketing-staging/code/MarketingHeader.tsx", "source_location": null, "source_url": null, "captured_at": null, "author": null, "contributor": null}], "edges": [{"source": "comp:MarketingHeader", "target": "comp:TorqrWordmark", "relation": "references", "confidence": "EXTRACTED", "confidence_score": 1.0, "source_file": ".graphify-marketing-staging/code/MarketingHeader.tsx", "source_location": null, "weight": 1.0}, {"source": "comp:MarketingHeader", "target": "comp:MobileNavSheet", "relation": "references", "confidence": "EXTRACTED", "confidence_score": 1.0, "source_file": ".graphify-marketing-staging/code/MarketingHeader.tsx", "source_location": null, "weight": 1.0}, {"source": "comp:MarketingHeader", "target": "ext:auth", "relation": "references", "confidence": "EXTRACTED", "confidence_score": 1.0, "source_file": ".graphify-marketing-staging/code/MarketingHeader.tsx", "source_location": null, "weight": 1.0}, {"source": "comp:MarketingHeader", "target": "ext:Button", "relation": "references", "confidence": "EXTRACTED", "confidence_score": 1.0, "source_file": ".graphify-marketing-staging/code/MarketingHeader.tsx", "source_location": null, "weight": 1.0}, {"source": "comp:MarketingHeader", "target": "nav:anchor#features", "relation": "references", "confidence": "EXTRACTED", "confidence_score": 1.0, "source_file": ".graphify-marketing-staging/code/MarketingHeader.tsx", "source_location": null, "weight": 1.0}, {"source": "comp:MarketingHeader", "target": "nav:anchor#pricing", "relation": "references", "confidence": "EXTRACTED", "confidence_score": 1.0, "source_file": ".graphify-marketing-staging/code/MarketingHeader.tsx", "source_location": null, "weight": 1.0}, {"source": "comp:MarketingHeader", "target": "nav:anchor#faq", "relation": "references", "confidence": "EXTRACTED", "confidence_score": 1.0, "source_file": ".graphify-marketing-staging/code/MarketingHeader.tsx", "source_location": null, "weight": 1.0}, {"source": "comp:MarketingHeader", "target": "nav:anchor#cta", "relation": "references", "confidence": "EXTRACTED", "confidence_score": 1.0, "source_file": ".graphify-marketing-staging/code/MarketingHeader.tsx", "source_location": null, "weight": 1.0}, {"source": "comp:MarketingHeader", "target": "nav:link/dashboard", "relation": "references", "confidence": "EXTRACTED", "confidence_score": 1.0, "source_file": ".graphify-marketing-staging/code/MarketingHeader.tsx", "source_location": null, "weight": 1.0}, {"source": "comp:MarketingHeader", "target": "nav:link/login", "relation": "references", "confidence": "EXTRACTED", "confidence_score": 1.0, "source_file": ".graphify-marketing-staging/code/MarketingHeader.tsx", "source_location": null, "weight": 1.0}, {"source": "comp:MarketingHeader", "target": "brand:voice.cta.30days", "relation": "references", "confidence": "EXTRACTED", "confidence_score": 1.0, "source_file": ".graphify-marketing-staging/code/MarketingHeader.tsx", "source_location": null, "weight": 1.0}], "hyperedges": [{"id": "hyper:nav-anchors", "label": "Marketing page anchor targets shared by header + footer + mobile nav", "members": ["nav:anchor#features", "nav:anchor#pricing", "nav:anchor#faq", "nav:anchor#cta", "comp:MarketingHeader", "comp:MarketingFooter", "comp:MobileNavSheet"], "relation": "references", "confidence": "EXTRACTED", "confidence_score": 1.0, "source_file": ".graphify-marketing-staging/code/MarketingHeader.tsx"}]}